booklab-0.8.dist-info/METADATA
booklab-0.8.dist-info/WHEEL
booklab-0.8.dist-info/entry_points.txt
booklab-0.8.dist-info/licenses/LICENSE
booklab/.pdm-python
booklab/.venv/.gitignore
booklab/.venv/CACHEDIR.TAG
booklab/.venv/bin/activate
booklab/.venv/bin/activate.csh
booklab/.venv/bin/activate.fish
booklab/.venv/bin/activate.nu
booklab/.venv/bin/activate.ps1
booklab/.venv/bin/activate_this.py
booklab/.venv/bin/python
booklab/.venv/bin/python3
booklab/.venv/bin/python3.10
booklab/.venv/lib/python3.10/site-packages/_virtualenv.pth
booklab/.venv/lib/python3.10/site-packages/_virtualenv.py
booklab/.venv/pyvenv.cfg
booklab/__init__.py
booklab/__main__.py
booklab/__version__.py
booklab/booklab_cli/README.md
booklab/booklab_cli/__init__.py
booklab/booklabd/__init__.py
booklab/booklabd/app_init.py
booklab/booklabd/routes.py
booklab/conf/__init__.py
booklab/conf/booklab_ext_url.py
booklab/conf/gunicorn_config.py
booklab/conf/nginx/booklab.conf
booklab/conf/nginx/proxy.conf
booklab/db_init.py
booklab/doc_src/810-DSGN/810.02-System_Landscape.md
booklab/doc_src/810-DSGN/810.05a-bcat_System_Process.md
booklab/doc_src/810-DSGN/810.05a-booklab_DLD_specs.md
booklab/doc_src/810-DSGN/810.05a-btmpl_System_Process.md
booklab/doc_src/810-DSGN/810.05a-dplb_System_Process.md
booklab/doc_src/810-DSGN/810.05a-edtm_System_Process.md
booklab/doc_src/810-DSGN/810.05a-newb_System_Process.md
booklab/doc_src/810-DSGN/810.05a-orgm_System_Process.md
booklab/doc_src/810-DSGN/810.05a-prvb_System_Process.md
booklab/doc_src/810-DSGN/810.05a-sysInit_System_Process.md
booklab/doc_src/CNAME
booklab/doc_src/__init__.py
booklab/doc_src/about/about.md
booklab/doc_src/about/about_template.md
booklab/doc_src/about/index.html
booklab/doc_src/bcat/bcat.md
booklab/doc_src/bcat/bcat_template.md
booklab/doc_src/bcat/index.html
booklab/doc_src/bcat/local-page.css
booklab/doc_src/bstatus/bstatus.html
booklab/doc_src/bstatus/bstatus_template.md
booklab/doc_src/bstatus/index.html
booklab/doc_src/bstatus/local-page.css
booklab/doc_src/dplb/_todo-here.txt
booklab/doc_src/dplb/index.html
booklab/doc_src/dplb/local-page.css
booklab-0.8.dist-info/RECORD
